{
  "node": {
    "004d72cd70323770e7b020b3a42ca3d88f78d768bf": {
      "workers": {
        "app/apps/kpi/page": {
          "moduleId": 1540,
          "async": false,
          "exportedName": "$$RSC_SERVER_ACTION_0",
          "filename": "src/app/apps/layout.tsx"
        }
      },
      "exportedName": "$$RSC_SERVER_ACTION_0",
      "filename": "src/app/apps/layout.tsx"
    },
    "40e85d1933695f0796d18323a6bcc1183434685f98": {
      "workers": {
        "app/apps/kpi/page": {
          "moduleId": 1540,
          "async": false,
          "exportedName": "fetchGLPLData",
          "filename": "src/app/apps/kpi/actions.ts"
        }
      },
      "exportedName": "fetchGLPLData",
      "filename": "src/app/apps/kpi/actions.ts"
    },
    "60cd5a9175019932ae8707d657144899db4b8ee710": {
      "workers": {
        "app/apps/kpi/page": {
          "moduleId": 1540,
          "async": false,
          "exportedName": "saveKPIReport",
          "filename": "src/app/apps/kpi/actions.ts"
        }
      },
      "exportedName": "saveKPIReport",
      "filename": "src/app/apps/kpi/actions.ts"
    },
    "405e7f4cc5fd443e8abf788de65c0420abb5b95399": {
      "workers": {
        "app/apps/kpi/page": {
          "moduleId": 1540,
          "async": false,
          "exportedName": "deleteKPIReport",
          "filename": "src/app/apps/kpi/actions.ts"
        }
      },
      "exportedName": "deleteKPIReport",
      "filename": "src/app/apps/kpi/actions.ts"
    },
    "403e6cc84be0131c882f5943b04e9e9000d035c7bc": {
      "workers": {
        "app/apps/kpi/page": {
          "moduleId": 1540,
          "async": false,
          "exportedName": "updateKPIBaseline",
          "filename": "src/app/apps/kpi/actions.ts"
        }
      },
      "exportedName": "updateKPIBaseline",
      "filename": "src/app/apps/kpi/actions.ts"
    },
    "00738ce73fb553954b8bb2ee95e157cebbdeda076c": {
      "workers": {
        "app/apps/kpi/page": {
          "moduleId": 1540,
          "async": false,
          "exportedName": "getKPIReports",
          "filename": "src/app/apps/kpi/actions.ts"
        }
      },
      "exportedName": "getKPIReports",
      "filename": "src/app/apps/kpi/actions.ts"
    },
    "00c6fb705447a24c83957ca8bac8023bc115cd0c2e": {
      "workers": {
        "app/apps/kpi/page": {
          "moduleId": 1540,
          "async": false,
          "exportedName": "getKPIBaseline",
          "filename": "src/app/apps/kpi/actions.ts"
        }
      },
      "exportedName": "getKPIBaseline",
      "filename": "src/app/apps/kpi/actions.ts"
    }
  },
  "edge": {}
}